pruun/__init__.py
pruun/commands.py
pruun/utils.py
pruun-0.4.0.dist-info/LICENSE
pruun-0.4.0.dist-info/METADATA
pruun-0.4.0.dist-info/WHEEL
pruun-0.4.0.dist-info/entry_points.txt
pruun-0.4.0.dist-info/top_level.txt
pruun-0.4.0.dist-info/RECORD
