Metadata-Version: 2.1
Name: pruun
Version: 0.4.0
Summary: Pruun is a CL utility for easily creating AWS lambda deployment packages within Python virtualenvs.
Home-page: https://github.com/alexkosj/pruun
Author: Alex Ko
Author-email: alexkosj@gmail.com
License: MIT
Platform: UNKNOWN
Classifier: License :: OSI Approved :: MIT License
Classifier: Programming Language :: Python :: 3.6
Classifier: Programming Language :: Python :: 3.7
Classifier: Programming Language :: Python :: 3.8
Requires-Dist: Click
